{
  "name": "bookmark_application_management",
  "title": "Bookmark Application Management",
  "description": "This template contains flows for managing bookmark apps in Okta, including creating new apps, updating existing ones, and deactivating them when no longer needed.",
  "connectors": [
    "okta"
  ],
  "details": {
    "stashCount": 1,
    "flowCount": 2,
    "flos": [
      {
        "id": "e8872b65-97c8-4ea5-9e57-f917ee13a214",
        "name": "1.1 Bookmark Application Management - Child Flow 1",
        "type": "HELPER",
        "screenshotURL": "https://d78vv2h34ll3s.cloudfront.net/static/catalog/workflows/bookmark_application_management/resources/40079c7fc59c59c5985b85985875ff5ff1ff.png"
      },
      {
        "id": "fcb2ad6a-676c-4b02-bf2c-56a0be878c05",
        "name": "1.0 Bookmark Application Management - Parent Flow",
        "type": "MAIN",
        "screenshotURL": "https://d78vv2h34ll3s.cloudfront.net/static/catalog/workflows/bookmark_application_management/resources/0443dc5f633437037c350f51f11f11f11f11.png"
      }
    ],
    "helperFlowsCount": 1,
    "mainFlowsCount": 1
  },
  "links": [
    {
      "destination": "https://github.com/okta/workflows-templates/blob/master/workflows/bookmark_application_management/readme.md",
      "title": "Setup Documentation"
    }
  ]
}
